LICENSE
MANIFEST.in
README.rst
distribute_setup.py
pokersleuth.py
setup.py
PokerSleuth.egg-info/PKG-INFO
PokerSleuth.egg-info/SOURCES.txt
PokerSleuth.egg-info/dependency_links.txt
PokerSleuth.egg-info/top_level.txt
PokerSleuth.egg-info/zip-safe