Metadata-Version: 1.1
Name: PokerSleuth
Version: 2.1.0.47
Summary: A wrapper for the Poker Sleuth Scriptable Equity Calculator
Home-page: http://pokersleuth.com/programmable-poker-calculator.shtml
Author: Stutzbach Enterprises, LLC
Author-email: daniel@stutzbachenterprises.com
License: BSD
Keywords: poker equity calculator odds
Platform: UNKNOWN
Classifier: Development Status :: 5 - Production/Stable
Classifier: Operating System :: Microsoft :: Windows
Classifier: Environment :: Win32 (MS Windows)
Classifier: Intended Audience :: Developers
Classifier: License :: OSI Approved :: BSD License
Classifier: Topic :: Games/Entertainment
Classifier: Topic :: Software Development :: Libraries :: Python Modules
Classifier: Topic :: Scientific/Engineering :: Mathematics
Classifier: Programming Language :: Python :: 2
Classifier: Programming Language :: Python :: 2.5
Classifier: Programming Language :: Python :: 2.6
Classifier: Programming Language :: Python :: 2.7
Classifier: Programming Language :: Python :: 3
Classifier: Programming Language :: Python :: 3.1
Classifier: Programming Language :: Python :: 3.2
Provides: pokersleuth
